stoked/__init__.py
stoked/analysis.py
stoked/cli.py
stoked/collisions.py
stoked/common.py
stoked/constraints.py
stoked/drag.py
stoked/electrodynamics.py
stoked/electrostatics.py
stoked/examples/bigaussian_potential.py
stoked/examples/ellipsoid.py
stoked/examples/estatics.py
stoked/examples/free_particle.py
stoked/examples/rt_coupling.py
stoked/examples/tt_coupling.py
stoked/forces.py
stoked/gravity.py
stoked/hydrodynamics.py
stoked/inertia.py
stoked/integrators/__init__.py
stoked/integrators/basic_integrator.py
stoked/integrators/integrator.py
stoked/integrators/predictor_corrector_integrator.py
stoked/potential.py
stoked/py.typed
stoked/solver.py
stoked/utility.py
stoked/van_der_waals.py
stoked/vis/__init__.py
stoked/vis/_internal.py
stoked/vis/animate_2d.py
stoked/vis/animate_3d.py
stoked/vis/colored_plot.py
stoked/vis/snapshots.py
stoked-1.0.0.dist-info/WHEEL
stoked-1.0.0.dist-info/entry_points.txt
stoked-1.0.0.dist-info/METADATA
stoked-1.0.0.dist-info/RECORD
