Metadata-Version: 2.3
Name: stoked
Version: 1.0.0
Summary: Simulation and visualization of Stokesian dynamics for N interacting particles
Author: John Parker
Author-email: John Parker <johnaparker@users.noreply.github.com>
Requires-Dist: matplotlib>=3.10.7
Requires-Dist: numpy>=2.3.3
Requires-Dist: numpy-quaternion>=2024.0.12
Requires-Dist: scipy>=1.16.2
Requires-Dist: tqdm>=4.67.1
Requires-Python: >=3.11
